streamz/__init__.py
streamz/batch.py
streamz/collection.py
streamz/compatibility.py
streamz/core.py
streamz/dask.py
streamz/graph.py
streamz/orderedweakset.py
streamz/sources.py
streamz/utils.py
streamz/utils_test.py
streamz/dataframe/__init__.py
streamz/dataframe/aggregations.py
streamz/dataframe/core.py
streamz/dataframe/tests/test_dataframes.py
streamz/tests/__init__.py
streamz/tests/py3_test_core.py
streamz/tests/test_batch.py
streamz/tests/test_core.py
streamz/tests/test_dask.py
streamz/tests/test_graph.py
streamz/tests/test_kafka.py
streamz_latest-0.3.0.dist-info/METADATA
streamz_latest-0.3.0.dist-info/RECORD
streamz_latest-0.3.0.dist-info/WHEEL
streamz_latest-0.3.0.dist-info/top_level.txt
