Metadata-Version: 2.1
Name: streamz-latest
Version: 0.3.0
Summary: Mrocklin streamz library. It's the latest version 
Home-page: http://github.com/mrocklin/streamz/
Maintainer: Matthew Rocklin
Maintainer-email: mrocklin@gmail.com
License: BSD
Keywords: streams
Platform: UNKNOWN
Requires-Dist: tornado
Requires-Dist: toolz
Requires-Dist: zict
Requires-Dist: six
